parsechain/__init__.py
parsechain/chains.py
parsechain/response.py
parsechain/wrappers.py
parsechain-0.0.2.dist-info/LICENSE.txt
parsechain-0.0.2.dist-info/METADATA
parsechain-0.0.2.dist-info/RECORD
parsechain-0.0.2.dist-info/WHEEL
parsechain-0.0.2.dist-info/top_level.txt
