Metadata-Version: 2.1
Name: parsechain
Version: 0.0.2
Summary: Making parsing concise
Home-page: http://github.com/Suor/parsechain
Author: Alexander Schepanovski
Author-email: suor.web@gmail.com
License: BSD
Platform: UNKNOWN
Classifier: Development Status :: 3 - Alpha
Classifier: License :: OSI Approved :: BSD License
Classifier: Operating System :: OS Independent
Classifier: Programming Language :: Python
Classifier: Programming Language :: Python :: 3
Classifier: Programming Language :: Python :: 3.6
Classifier: Programming Language :: Python :: Implementation :: CPython
Classifier: Topic :: Software Development :: Libraries :: Python Modules
Classifier: Topic :: Text Processing :: Markup :: HTML
Classifier: Intended Audience :: Developers
Requires-Dist: funcy (<2.0,>=1.10.2)
Requires-Dist: lxml
Requires-Dist: cssselect
